opensitua_http/__init__.py
opensitua_http/filesystem.py
opensitua_http/http.py
opensitua_http/mapfile.py
opensitua_http/stime.py
opensitua_http/strings.py
opensitua_http-0.0.72.dist-info/LICENSE
opensitua_http-0.0.72.dist-info/METADATA
opensitua_http-0.0.72.dist-info/WHEEL
opensitua_http-0.0.72.dist-info/top_level.txt
opensitua_http-0.0.72.dist-info/RECORD
