Metadata-Version: 2.1
Name: opensitua-http
Version: 0.0.72
Summary: A core functions package
Home-page: https://github.com/valluzzi/opensitua_http.git
Author: Valerio Luzzi
Author-email: valluzzi@gmail.com
License: UNKNOWN
Platform: UNKNOWN
Classifier: Programming Language :: Python :: 3
Classifier: License :: OSI Approved :: MIT License
Classifier: Operating System :: OS Independent
License-File: LICENSE
Requires-Dist: jinja2
Requires-Dist: six
Requires-Dist: opensitua-core
